rotatesecretkey/__init__.py
rotatesecretkey/apps.py
rotatesecretkey/middleware.py
rotatesecretkey/sessions.py
rotatesecretkey/signing.py
django_rotate_secret_key-0.3.dist-info/LICENSE
django_rotate_secret_key-0.3.dist-info/METADATA
django_rotate_secret_key-0.3.dist-info/WHEEL
django_rotate_secret_key-0.3.dist-info/top_level.txt
django_rotate_secret_key-0.3.dist-info/RECORD
