Metadata-Version: 1.0
Name: django-rotate-secret-key
Version: 0.3
Summary: Rotate your Django secret
Home-page: https://github.com/EralpB/django-rotate-secret-key/
Author: Eralp Bayraktar
Author-email: imeralpb@gmail.com
License: MIT
Platform: UNKNOWN
